asndb/__init__.py
asndb/asndb.py
asndb/main.py
asndb-1.0.0.dist-info/METADATA
asndb-1.0.0.dist-info/WHEEL
asndb-1.0.0.dist-info/entry_points.txt
asndb-1.0.0.dist-info/top_level.txt
asndb-1.0.0.dist-info/RECORD
