Metadata-Version: 2.4
Name: asndb
Version: 1.0.0
Summary: A simple Python CLI + library for looking up ASNs by IP or AS number. Uses BBOT.IO API.
Author: TheTechromancer
Requires-Python: >=3.9
Requires-Dist: cachetools>=6.2.1
Requires-Dist: httpx>=0.28.1
Requires-Dist: radixtarget>=4.0.1
Requires-Dist: typer>=0.19.2
